jom.py
jom-0.0.6.dist-info/LICENSE
jom-0.0.6.dist-info/METADATA
jom-0.0.6.dist-info/WHEEL
jom-0.0.6.dist-info/top_level.txt
jom-0.0.6.dist-info/RECORD
