Metadata-Version: 2.1
Name: jom
Version: 0.0.6
Summary: simple json data manager targeting model.JsonField in (djano framework)
Home-page: https://github.com/iamhusseinnaim/jom.git
Author: Hussein Naim
Author-email: phusseinnaim@gmail.com
License: UNKNOWN
Platform: UNKNOWN
Classifier: Programming Language :: Python :: 3
Classifier: License :: OSI Approved :: MIT License
Classifier: Operating System :: OS Independent
Requires-Python: >=3.9
License-File: LICENSE
